odoo9_addon_website_sale_qty-9.0.1.0.1-py2.7-nspkg.pth
odoo9_addon_website_sale_qty-9.0.1.0.1.dist-info/DESCRIPTION.rst
odoo9_addon_website_sale_qty-9.0.1.0.1.dist-info/METADATA
odoo9_addon_website_sale_qty-9.0.1.0.1.dist-info/RECORD
odoo9_addon_website_sale_qty-9.0.1.0.1.dist-info/WHEEL
odoo9_addon_website_sale_qty-9.0.1.0.1.dist-info/metadata.json
odoo9_addon_website_sale_qty-9.0.1.0.1.dist-info/namespace_packages.txt
odoo9_addon_website_sale_qty-9.0.1.0.1.dist-info/top_level.txt
odoo_addons/website_sale_qty/README.rst
odoo_addons/website_sale_qty/__init__.py
odoo_addons/website_sale_qty/__openerp__.py
odoo_addons/website_sale_qty/demo/product_pricelist_item_demo.xml
odoo_addons/website_sale_qty/i18n/bg.po
odoo_addons/website_sale_qty/i18n/ca.po
odoo_addons/website_sale_qty/i18n/de.po
odoo_addons/website_sale_qty/i18n/es.po
odoo_addons/website_sale_qty/i18n/es_MX.po
odoo_addons/website_sale_qty/i18n/fi.po
odoo_addons/website_sale_qty/i18n/fr.po
odoo_addons/website_sale_qty/i18n/fr_CH.po
odoo_addons/website_sale_qty/i18n/hr.po
odoo_addons/website_sale_qty/i18n/hr_HR.po
odoo_addons/website_sale_qty/i18n/it.po
odoo_addons/website_sale_qty/i18n/pt_BR.po
odoo_addons/website_sale_qty/i18n/ro.po
odoo_addons/website_sale_qty/i18n/sl.po
odoo_addons/website_sale_qty/i18n/tr_TR.po
odoo_addons/website_sale_qty/i18n/vi_VN.po
odoo_addons/website_sale_qty/i18n/zh_CN.po
odoo_addons/website_sale_qty/models/__init__.py
odoo_addons/website_sale_qty/models/product_template.py
odoo_addons/website_sale_qty/security/ir.model.access.csv
odoo_addons/website_sale_qty/static/description/icon.png
odoo_addons/website_sale_qty/static/src/js/website_sale_qty.js
odoo_addons/website_sale_qty/static/tests/js/website_sale_qty.tour.js
odoo_addons/website_sale_qty/tests/__init__.py
odoo_addons/website_sale_qty/tests/test_js.py
odoo_addons/website_sale_qty/tests/test_product_template.py
odoo_addons/website_sale_qty/views/website_sale_qty.xml
