Metadata-Version: 2.0
Name: odoo9-addon-website-sale-qty
Version: 9.0.1.0.1
Summary: Add price tier radio buttons to product pages in website shop
Home-page: https://laslabs.com/
Author: LasLabs, Odoo Community Association (OCA)
Author-email: support@odoo-community.org
License: LGPL-3
Platform: UNKNOWN
Classifier: Programming Language :: Python
Classifier: Framework :: Odoo
Classifier: License :: OSI Approved :: GNU Lesser General Public License v3 (LGPLv3)
Requires-Python: ~=2.7
Requires-Dist: odoo (<9.1a,>=9.0a)
